{
    "4": {
        "films": [
            "1",
            "5"
        ],
        "pilots": [
            "1",
            "5"
        ]
    },
    "6": {
        "films": [
            "1"
        ],
        "pilots": [
            "1"
        ]
    },
    "7": {
        "films": [
            "1"
        ],
        "pilots": [
            "1"
        ]
    },
    "8": {
        "films": [
            "1",
            "2",
            "3"
        ],
        "pilots": [
            "1",
            "2",
            "3"
        ]
    },
    "14": {
        "films": [
            "2"
        ],
        "pilots": [
            "1",
            "18"
        ]
    },
    "16": {
        "films": [
            "2",
            "3"
        ],
        "pilots": [
            "2",
            "3"
        ]
    },
    "18": {
        "films": [
            "2",
            "3"
        ],
        "pilots": [
            "2",
            "3"
        ]
    },
    "19": {
        "films": [
            "2",
            "3"
        ],
        "pilots": [
            "13"
        ]
    },
    "20": {
        "films": [
            "2"
        ],
        "pilots": [
            "2"
        ]
    },
    "24": {
        "films": [
            "3"
        ],
        "pilots": [
            "3"
        ]
    },
    "25": {
        "films": [
            "3"
        ],
        "pilots": [
            "3"
        ]
    },
    "26": {
        "films": [
            "3"
        ],
        "pilots": [
            "3"
        ]
    },
    "30": {
        "films": [
            "3"
        ],
        "pilots": [
            "1",
            "5"
        ]
    },
    "33": {
        "films": [
            "4",
            "6"
        ],
        "pilots": [
            "4",
            "6"
        ]
    },
    "34": {
        "films": [
            "4"
        ],
        "pilots": [
            "4"
        ]
    },
    "35": {
        "films": [
            "4"
        ],
        "pilots": [
            "4"
        ]
    },
    "36": {
        "films": [
            "4"
        ],
        "pilots": [
            "4"
        ]
    },
    "37": {
        "films": [
            "4"
        ],
        "pilots": [
            "4"
        ]
    },
    "38": {
        "films": [
            "4"
        ],
        "pilots": [
            "10",
            "32"
        ]
    },
    "42": {
        "films": [
            "4"
        ],
        "pilots": [
            "44"
        ]
    },
    "44": {
        "films": [
            "5"
        ],
        "pilots": [
            "11"
        ]
    },
    "45": {
        "films": [
            "5"
        ],
        "pilots": [
            "70"
        ]
    },
    "46": {
        "films": [
            "5"
        ],
        "pilots": [
            "11"
        ]
    },
    "50": {
        "films": [
            "5",
            "6"
        ],
        "pilots": [
            "5",
            "6"
        ]
    },
    "51": {
        "films": [
            "5"
        ],
        "pilots": [
            "5"
        ]
    },
    "53": {
        "films": [
            "5",
            "6"
        ],
        "pilots": [
            "5",
            "6"
        ]
    },
    "54": {
        "films": [
            "5"
        ],
        "pilots": [
            "5"
        ]
    },
    "55": {
        "films": [
            "5"
        ],
        "pilots": [
            "67"
        ]
    },
    "56": {
        "films": [
            "5",
            "6"
        ],
        "pilots": [
            "5",
            "6"
        ]
    },
    "57": {
        "films": [
            "5"
        ],
        "pilots": [
            "5"
        ]
    },
    "60": {
        "films": [
            "6"
        ],
        "pilots": [
            "79"
        ]
    },
    "62": {
        "films": [
            "6"
        ],
        "pilots": [
            "6"
        ]
    },
    "67": {
        "films": [
            "6"
        ],
        "pilots": [
            "6"
        ]
    },
    "69": {
        "films": [
            "6"
        ],
        "pilots": [
            "6"
        ]
    },
    "70": {
        "films": [
            "6"
        ],
        "pilots": [
            "6"
        ]
    },
    "71": {
        "films": [
            "6"
        ],
        "pilots": [
            "6"
        ]
    },
    "72": {
        "films": [
            "6"
        ],
        "pilots": [
            "6"
        ]
    },
    "73": {
        "films": [
            "6"
        ],
        "pilots": [
            "6"
        ]
    },
    "76": {
        "films": [
            "6"
        ],
        "pilots": [
            "6"
        ]
    }
}